scilogger/__init__.py
scilogger/scilogger.ini
scilogger/scilogger.py
scilogger/version.txt
scilogger-1.2.5.dist-info/licenses/LICENSE.txt
scilogger-1.2.5.dist-info/METADATA
scilogger-1.2.5.dist-info/WHEEL
scilogger-1.2.5.dist-info/top_level.txt
scilogger-1.2.5.dist-info/RECORD
