Metadata-Version: 2.4
Name: scilogger
Version: 1.2.5
Summary: SciLogger - Logging for Scientific Applications
Author-email: Thomas Guillod <guillod@otvam.ch>
Maintainer-email: Thomas Guillod <guillod@otvam.ch>
License-Expression: BSD-2-Clause
Project-URL: Homepage, https://github.com/otvam/scilogger
Project-URL: Repository, https://github.com/otvam/scilogger
Project-URL: Releases, https://github.com/otvam/scilogger/releases
Project-URL: Issues, https://github.com/otvam/scilogger/issues
Project-URL: Tags, https://github.com/otvam/scilogger/tags
Keywords: Python,Timing,Logging,Logger,Log
Classifier: Development Status :: 5 - Production/Stable
Classifier: Intended Audience :: Science/Research
Classifier: Operating System :: OS Independent
Classifier: Programming Language :: Python :: 3
Classifier: Topic :: Scientific/Engineering
Classifier: Natural Language :: English
Classifier: Environment :: Console
Requires-Python: >=3.9
License-File: LICENSE.txt
Provides-Extra: dev
Requires-Dist: pip>=24.3; extra == "dev"
Requires-Dist: build>=1.2; extra == "dev"
Provides-Extra: test
Requires-Dist: ruff>=0.8; extra == "test"
Dynamic: license-file
